blehhconfig.py
blehhconfig-1.0.3.dist-info/licenses/LICENSE
blehhconfig-1.0.3.dist-info/METADATA
blehhconfig-1.0.3.dist-info/WHEEL
blehhconfig-1.0.3.dist-info/entry_points.txt
blehhconfig-1.0.3.dist-info/top_level.txt
blehhconfig-1.0.3.dist-info/RECORD
