Metadata-Version: 2.4
Name: blehhconfig
Version: 1.0.3
Summary: Hay Hoist Bluetooth Configuration Tool
Author-email: Nathan Fraser <ndf-zz@6-v.org>
License-Expression: MIT
Project-URL: homepage, https://github.com/ndf-zz/remootio-adapter/util/blehhconfig
Keywords: tk,ble,bleak,bluetooth
Classifier: Development Status :: 3 - Alpha
Classifier: Environment :: Win32 (MS Windows)
Classifier: Environment :: X11 Applications
Classifier: Natural Language :: English
Classifier: Operating System :: OS Independent
Classifier: Programming Language :: Python :: 3
Classifier: Topic :: Scientific/Engineering
Requires-Python: >=3.9
License-File: LICENSE
Requires-Dist: bleak
Dynamic: license-file
